liangent/__init__.py
liangent/agents_md_template
liangent/cli.py
liangent/client.py
liangent/config.py
liangent/env_template
liangent/server.py
liangent/types.py
liangent/core/__init__.py
liangent/core/agent.py
liangent/core/llm.py
liangent/core/prompt_engine.py
liangent/memory/__init__.py
liangent/memory/db.py
liangent/memory/manager.py
liangent/memory/models.py
liangent/prompts/system.j2
liangent/tools/__init__.py
liangent/tools/demo_tools.py
liangent/tools/registry.py
liangent/tools/sandbox.py
liangent/tools/shell_env.py
liangent/tools/builtin/shell.py
liangent-0.0.18.dist-info/licenses/LICENSE
liangent-0.0.18.dist-info/METADATA
liangent-0.0.18.dist-info/WHEEL
liangent-0.0.18.dist-info/entry_points.txt
liangent-0.0.18.dist-info/top_level.txt
liangent-0.0.18.dist-info/RECORD
