Metadata-Version: 2.4
Name: liangent
Version: 0.0.18
Summary: A lightweight agent framework
Author: Liang
License: MIT License
Classifier: Programming Language :: Python :: 3
Classifier: License :: OSI Approved :: MIT License
Classifier: Operating System :: OS Independent
Requires-Python: >=3.10
License-File: LICENSE
Requires-Dist: fastapi
Requires-Dist: uvicorn
Requires-Dist: sqlalchemy
Requires-Dist: jinja2
Requires-Dist: pydantic
Requires-Dist: pydantic-settings
Requires-Dist: requests
Requires-Dist: python-dotenv
Requires-Dist: openai
Requires-Dist: socksio
Dynamic: license-file
